servly/__init__.py
servly/cli.py
servly/logs.py
servly/service.py
servly-0.3.1.dist-info/METADATA
servly-0.3.1.dist-info/WHEEL
servly-0.3.1.dist-info/entry_points.txt
servly-0.3.1.dist-info/top_level.txt
servly-0.3.1.dist-info/RECORD
