Metadata-Version: 2.4
Name: servly
Version: 0.3.1
Summary: simple process manager
Author-email: simpxx <simpxx@gmail.com>
License: MIT
Keywords: command-line,tool
Classifier: Programming Language :: Python :: 3
Classifier: License :: OSI Approved :: MIT License
Classifier: Operating System :: OS Independent
Requires-Python: >=3.12
Requires-Dist: psutil>=7.0.0
Requires-Dist: pyyaml>=6.0.2
Requires-Dist: rich>=14.0.0
